{
  "data": {
    "instruments": {
      "pageCursors": {
        "all": [
          {
            "cursor": ""
          },
          {
            "cursor": "MTA"
          },
          {
            "cursor": "MjA"
          },
          {
            "cursor": "MzA"
          }
        ]
      },
      "totalPages": 4,
      "totalCount": 33,
      "pageInfo": {
        "hasNextPage": true
      },
      "nodes": [
        {
          "__typename": "Fund",
          "currency": {
            "id": null,
            "isoCode": "USD"
          },
          "instrumentLabel": {
            "topSellingPercentile": null,
            "topAumPercentile": null
          },
          "wiCode": "Naresh",
          "instrumentName": "American Funds Growth Fund of Amer A",
          "standardDeviation": {
            "threeYear": 11.842
          },
          "returns": {
            "threeYear": 1.344
          },
          "strategicAssetAllocation": {
            "cash": "0292.232",
            "bond": "0.0",
            "stock": "94.01503",
            "alternatives": "0.06084"
          },
          "expenseRatio": 0.62,
          "sharpeRatio": {
            "threeYear": 1.246
          },
          "incomeGrowthFocus": "Growth",
          "minimumInitialInvestment": 250,
          "previousClosePrice": null
        },
        {
          "__typename": "Fund",
          "currency": {
            "id": null,
            "isoCode": "USD"
          },
          "instrumentLabel": {
            "topSellingPercentile": null,
            "topAumPercentile": null
          },
          "wiCode": "WI-CORE-22145",
          "instrumentName": "JPMorgan US Government MMkt Eagle",
          "standardDeviation": {
            "threeYear": 0.189
          },
          "returns": {
            "threeYear": 0.057
          },
          "strategicAssetAllocation": {
            "cash": "66.39644",
            "bond": "33.52149",
            "stock": "0.08207",
            "alternatives": "0.0"
          },
          "expenseRatio": 0.71,
          "sharpeRatio": {
            "threeYear": -11.66
          },
          "incomeGrowthFocus": "Money Mkt - Government",
          "minimumInitialInvestment": 1000,
          "previousClosePrice": null
        },
        {
          "__typename": "Fund",
          "currency": {
            "id": null,
            "isoCode": "USD"
          },
          "instrumentLabel": {
            "topSellingPercentile": null,
            "topAumPercentile": null
          },
          "wiCode": "WI-CORE-22147",
          "instrumentName": "Fidelity速 500 Index",
          "standardDeviation": {
            "threeYear": 10.856
          },
          "returns": {
            "threeYear": 1.21
          },
          "strategicAssetAllocation": {
            "cash": "0.38731",
            "bond": "0.02123",
            "stock": "99.59146",
            "alternatives": "0.0"
          },
          "expenseRatio": 0.02,
          "sharpeRatio": {
            "threeYear": 1.211
          },
          "incomeGrowthFocus": "Growth and Income",
          "minimumInitialInvestment": 0,
          "previousClosePrice": null
        },
        {
          "__typename": "Fund",
          "currency": {
            "id": null,
            "isoCode": "USD"
          },
          "instrumentLabel": {
            "topSellingPercentile": null,
            "topAumPercentile": null
          },
          "wiCode": "WI-CORE-22148",
          "instrumentName": "Vanguard Prime Money Market Investor",
          "standardDeviation": {
            "threeYear": 0.201
          },
          "returns": {
            "threeYear": 0.114
          },
          "strategicAssetAllocation": {
            "cash": "87.67942",
            "bond": "11.08355",
            "stock": "0.0",
            "alternatives": "1.23703"
          },
          "expenseRatio": 0.16,
          "sharpeRatio": {
            "threeYear": 0.758
          },
          "incomeGrowthFocus": "Money Mkt - Taxable",
          "minimumInitialInvestment": 3000,
          "previousClosePrice": null
        },
        {
          "__typename": "Fund",
          "currency": {
            "id": null,
            "isoCode": "USD"
          },
          "instrumentLabel": {
            "topSellingPercentile": null,
            "topAumPercentile": null
          },
          "wiCode": "WI-CORE-22149",
          "instrumentName": "Fidelity速 Government Cash Reserves",
          "standardDeviation": {
            "threeYear": 0.207
          },
          "returns": {
            "threeYear": 0.079
          },
          "strategicAssetAllocation": {
            "cash": "44.85503",
            "bond": "56.29999",
            "stock": "0.0",
            "alternatives": "-1.15502"
          },
          "expenseRatio": 0.38,
          "sharpeRatio": {
            "threeYear": -10.562
          },
          "incomeGrowthFocus": "Money Mkt - Taxable",
          "minimumInitialInvestment": 0,
          "previousClosePrice": null
        },
        {
          "__typename": "Fund",
          "currency": {
            "id": null,
            "isoCode": "USD"
          },
          "instrumentLabel": {
            "topSellingPercentile": null,
            "topAumPercentile": null
          },
          "wiCode": "WI-CORE-22150",
          "instrumentName": "Fidelity速 Government MMkt",
          "standardDeviation": {
            "threeYear": 0.209
          },
          "returns": {
            "threeYear": 0.075
          },
          "strategicAssetAllocation": {
            "cash": "81.49896",
            "bond": "21.51381",
            "stock": "0.0",
            "alternatives": "-3.01276"
          },
          "expenseRatio": 0.42,
          "sharpeRatio": {
            "threeYear": -12.796
          },
          "incomeGrowthFocus": "Money Mkt - Government",
          "minimumInitialInvestment": 0,
          "previousClosePrice": null
        },
        {
          "__typename": "Fund",
          "currency": {
            "id": null,
            "isoCode": "USD"
          },
          "instrumentLabel": {
            "topSellingPercentile": null,
            "topAumPercentile": null
          },
          "wiCode": "WI-CORE-22151",
          "instrumentName": "Fidelity速 Inv MM Fds Government III",
          "standardDeviation": {
            "threeYear": 0.21
          },
          "returns": {
            "threeYear": 0.073
          },
          "strategicAssetAllocation": {
            "cash": "43.22597",
            "bond": "58.46254",
            "stock": "0.0",
            "alternatives": "-1.68852"
          },
          "expenseRatio": 0.46,
          "sharpeRatio": {
            "threeYear": -13.926
          },
          "incomeGrowthFocus": "Money Mkt - Government",
          "minimumInitialInvestment": 1000000,
          "previousClosePrice": null
        },
        {
          "__typename": "Fund",
          "currency": {
            "id": null,
            "isoCode": "USD"
          },
          "instrumentLabel": {
            "topSellingPercentile": null,
            "topAumPercentile": null
          },
          "wiCode": "WI-CORE-22152",
          "instrumentName": "Goldman Sachs FS Government Instl",
          "standardDeviation": {
            "threeYear": 0.21
          },
          "returns": {
            "threeYear": 0.096
          },
          "strategicAssetAllocation": {
            "cash": "64.88081",
            "bond": "35.11919",
            "stock": "0.0",
            "alternatives": "0.0"
          },
          "expenseRatio": 0.19,
          "sharpeRatio": {
            "threeYear": -5.714
          },
          "incomeGrowthFocus": "Money Mkt - Government",
          "minimumInitialInvestment": 10000000,
          "previousClosePrice": null
        },
        {
          "__typename": "Fund",
          "currency": {
            "id": null,
            "isoCode": "USD"
          },
          "instrumentLabel": {
            "topSellingPercentile": null,
            "topAumPercentile": null
          },
          "wiCode": "WI-CORE-22153",
          "instrumentName": "JPMorgan US Government MMkt Instl",
          "standardDeviation": {
            "threeYear": 0.206
          },
          "returns": {
            "threeYear": 0.093
          },
          "strategicAssetAllocation": {
            "cash": "66.39644",
            "bond": "33.52149",
            "stock": "0.08207",
            "alternatives": "0.0"
          },
          "expenseRatio": 0.26,
          "sharpeRatio": {
            "threeYear": -6.425
          },
          "incomeGrowthFocus": "Money Mkt - Government",
          "minimumInitialInvestment": 10000000,
          "previousClosePrice": null
        },
        {
          "__typename": "Fund",
          "currency": {
            "id": null,
            "isoCode": "USD"
          },
          "instrumentLabel": {
            "topSellingPercentile": null,
            "topAumPercentile": null
          },
          "wiCode": "WI-CORE-22143",
          "instrumentName": "JPMorgan US Government MMkt Investor",
          "standardDeviation": {
            "threeYear": 0.204
          },
          "returns": {
            "threeYear": 0.069
          },
          "strategicAssetAllocation": {
            "cash": "66.39644",
            "bond": "33.52149",
            "stock": "0.08207",
            "alternatives": "0.0"
          },
          "expenseRatio": 0.51,
          "sharpeRatio": {
            "threeYear": -13.84
          },
          "incomeGrowthFocus": "Money Mkt - Government",
          "minimumInitialInvestment": 1000000,
          "previousClosePrice": null
        }
      ]
    }
  }
}
